nxpy_nonblocking_subprocess-1.0.0-py3.7-nspkg.pth
nxpy/core/nonblocking_subprocess/__init__.py
nxpy/core/nonblocking_subprocess/nonblocking_subprocess.py
nxpy_nonblocking_subprocess-1.0.0.dist-info/LICENSE.txt
nxpy_nonblocking_subprocess-1.0.0.dist-info/METADATA
nxpy_nonblocking_subprocess-1.0.0.dist-info/WHEEL
nxpy_nonblocking_subprocess-1.0.0.dist-info/namespace_packages.txt
nxpy_nonblocking_subprocess-1.0.0.dist-info/top_level.txt
nxpy_nonblocking_subprocess-1.0.0.dist-info/RECORD
